README
cloudsql.py
dev_server.py
saecloud
setup.py
sae/__init__.py
sae/channel.js
sae/channel.py
sae/conf.py
sae/const.py
sae/core.py
sae/kvdb.py
sae/mail.py
sae/memcache.py
sae/sae_signature.py
sae/storage.py
sae/taskqueue.py
sae/util.py
sae/_restful_mysql/__init__.py
sae/_restful_mysql/_mysql.py
sae/_restful_mysql/_mysql_exceptions.py
sae/_restful_mysql/connections.py
sae/_restful_mysql/converters.py
sae/_restful_mysql/cursors.py
sae/_restful_mysql/monkey.py
sae/_restful_mysql/release.py
sae/_restful_mysql/times.py
sae/_restful_mysql/constants/CLIENT.py
sae/_restful_mysql/constants/CR.py
sae/_restful_mysql/constants/ER.py
sae/_restful_mysql/constants/FIELD_TYPE.py
sae/_restful_mysql/constants/FLAG.py
sae/_restful_mysql/constants/REFRESH.py
sae/_restful_mysql/constants/__init__.py
sae/ext/__init__.py
sae/ext/shell.py
sae/ext/django/__init__.py
sae/ext/django/mail/__init__.py
sae/ext/django/mail/backend.py
sae/ext/django/storage/__init__.py
sae/ext/django/storage/backend.py
sae/ext/storage/__init__.py
sae/ext/storage/monkey.py
sae_python_dev.egg-info/PKG-INFO
sae_python_dev.egg-info/SOURCES.txt
sae_python_dev.egg-info/dependency_links.txt
sae_python_dev.egg-info/not-zip-safe
sae_python_dev.egg-info/pbr.json
sae_python_dev.egg-info/requires.txt
sae_python_dev.egg-info/top_level.txt