Metadata-Version: 1.0
Name: sae-python-dev
Version: 1.3.3
Summary: SAE Python development server
Home-page: http://python.sinaapp.com
Author: SAE Python Team
Author-email: saemail@sina.cn
License: UNKNOWN
Platform: any
